README.md
setup.py
bin/clitui
bin/clitui.bat
clitui/__init__.py
clitui/__main__.py
clitui/charsheet.py
clitui/curser_control.py
clitui/display.py
clitui/font.py
clitui/menu.py
clitui/terminal_size.py
clitui.egg-info/PKG-INFO
clitui.egg-info/SOURCES.txt
clitui.egg-info/dependency_links.txt
clitui.egg-info/not-zip-safe
clitui.egg-info/top_level.txt