Metadata-Version: 2.1
Name: clitui
Version: 0.2.1
Summary: A tool to help make command line drawing easier.
Home-page: https://github.com/cowboy8625/CLITUI
Author: Cowboy8625
Author-email: cowboy8625@protonmail.com
License: Apache License
Platform: UNKNOWN
